buildh/UI.py
buildh/__init__.py
buildh/core.py
buildh/geometry.py
buildh/hydrogens.py
buildh/init_dics.py
buildh/lipids.py
buildh/utils.py
buildh/writers.py
buildh/lipids/Berger_CHOL.json
buildh/lipids/Berger_DOPC.json
buildh/lipids/Berger_DPPC.json
buildh/lipids/Berger_POPC.json
buildh/lipids/Berger_POPE.json
buildh/lipids/Berger_POPS.json
buildh/lipids/CHARMM36UA_DPPC.json
buildh/lipids/CHARMM36_POPC.json
buildh/lipids/GROMOS53A6L_DPPC.json
buildh/lipids/GROMOSCKP_POPC.json
buildh/lipids/GROMOSCKP_POPS.json
buildh-1.6.1.dist-info/AUTHORS
buildh-1.6.1.dist-info/LICENSE.txt
buildh-1.6.1.dist-info/METADATA
buildh-1.6.1.dist-info/WHEEL
buildh-1.6.1.dist-info/entry_points.txt
buildh-1.6.1.dist-info/top_level.txt
buildh-1.6.1.dist-info/RECORD
