Metadata-Version: 2.1
Name: buildh
Version: 1.6.1
Summary: Build hydrogen atoms from united-atom molecular dynamics of lipids and calculate the order parameters.
Home-page: https://github.com/patrickfuchs/buildH
Author: Hubert Santuz, Amélie Bâcle, Pierre Poulain, Patrick Fuchs
Author-email: patrick.fuchs@u-paris.fr
License: BSD 3-Clause License
Keywords: lipds,order parameters,united atom,molecular dynamics simulation
Platform: UNKNOWN
Classifier: Development Status :: 4 - Beta
Classifier: Intended Audience :: Science/Research
Classifier: Topic :: Scientific/Engineering
Classifier: Topic :: Scientific/Engineering :: Bio-Informatics
Classifier: Topic :: Scientific/Engineering :: Chemistry
Classifier: Natural Language :: English
Classifier: Programming Language :: Python
Classifier: Programming Language :: Python :: 3
Classifier: Programming Language :: Python :: 3.6
Classifier: Programming Language :: Python :: 3.7
Classifier: Programming Language :: Python :: 3.8
Classifier: Programming Language :: Python :: 3.9
Requires-Python: >=3.6
License-File: LICENSE.txt
License-File: AUTHORS
Requires-Dist: numpy
Requires-Dist: pandas
Requires-Dist: MDAnalysis
Requires-Dist: numba
Provides-Extra: test
Requires-Dist: pytest ; extra == 'test'
